vibe_cmds/__init__.py
vibe_cmds/ass.py
vibe_cmds/common.py
vibe_cmds/css.py
vibe_cmds/dss.py
vibe_cmds/fss.py
vibe_cmds-1.0.0.dist-info/licenses/LICENSE
vibe_cmds-1.0.0.dist-info/METADATA
vibe_cmds-1.0.0.dist-info/WHEEL
vibe_cmds-1.0.0.dist-info/entry_points.txt
vibe_cmds-1.0.0.dist-info/top_level.txt
vibe_cmds-1.0.0.dist-info/RECORD
