Metadata-Version: 2.4
Name: vibe-cmds
Version: 1.0.0
Summary: Useful vibe coding cli commands.
Author: monosolo101
Author-email: monosolo1on1@gmail.com
Keywords: git,utility,commands
Requires-Python: >=3.6
License-File: LICENSE
Requires-Dist: gitpython>=3.1.0
Requires-Dist: pillow==11.3.0
Dynamic: author
Dynamic: author-email
Dynamic: description
Dynamic: description-content-type
Dynamic: keywords
Dynamic: license-file
Dynamic: requires-dist
Dynamic: requires-python
Dynamic: summary
